{
  "gitSyncId": "678909fc503b763d46bbe8f3_b84b81d6-7953-4e7c-b793-97bb3126de04",
  "id": "Qly chương trình từ thiện_Query6",
  "pluginId": "mysql-plugin",
  "pluginType": "DB",
  "unpublishedAction": {
    "actionConfiguration": {
      "body": "UPDATE ChuongTrinhTuThien\nSET trangThai = 'Hoạt động'\nWHERE id = '{{Table3.selectedRow.id}}';",
      "encodeParamsToggle": true,
      "paginationType": "NONE",
      "pluginSpecifiedTemplates": [
        {
          "value": true
        }
      ],
      "timeoutInMillisecond": 10000
    },
    "confirmBeforeExecute": false,
    "datasource": {
      "id": "Untitled datasource 2 #1",
      "isAutoGenerated": false,
      "name": "Untitled datasource 2 #1",
      "pluginId": "mysql-plugin"
    },
    "dynamicBindingPathList": [
      {
        "key": "body"
      }
    ],
    "executeOnLoad": false,
    "name": "Query6",
    "pageId": "Qly chương trình từ thiện",
    "userSetOnLoad": false
  }
}