{
  "gitSyncId": "678909fc503b763d46bbe8f3_f35dc13a-908e-4be4-afd8-dcf721b0a343",
  "id": "Theo dõi tiến độ chương trình_Query1",
  "pluginId": "mysql-plugin",
  "pluginType": "DB",
  "unpublishedAction": {
    "actionConfiguration": {
      "body": "SELECT \n    NguoiDung.tenNguoiDung, \n    ChuongTrinhTuThien.tenChuongTrinh, \n    ChuongTrinhTuThien.diaDiem, \n    ChuongTrinhTuThien.ngayBatDau \nFROM \n    TheoDoi\nINNER JOIN \n    NguoiDung ON TheoDoi.soDienThoai = NguoiDung.soDienThoai\nINNER JOIN \n    ChuongTrinhTuThien ON TheoDoi.idChuongTrinh = ChuongTrinhTuThien.id\nWHERE \n    ChuongTrinhTuThien.trangThai = 'Hoạt động';\n",
      "encodeParamsToggle": true,
      "paginationType": "NONE",
      "pluginSpecifiedTemplates": [
        {
          "value": true
        }
      ],
      "timeoutInMillisecond": 10000
    },
    "confirmBeforeExecute": false,
    "datasource": {
      "id": "Untitled datasource 2 #1",
      "isAutoGenerated": false,
      "name": "Untitled datasource 2 #1",
      "pluginId": "mysql-plugin"
    },
    "dynamicBindingPathList": [],
    "executeOnLoad": true,
    "name": "Query1",
    "pageId": "Theo dõi tiến độ chương trình",
    "userSetOnLoad": false
  }
}